juju/__init__.py
juju/_jasyncio.py
juju/access.py
juju/action.py
juju/annotation.py
juju/annotationhelper.py
juju/application.py
juju/bundle.py
juju/charm.py
juju/charmhub.py
juju/constraints.py
juju/controller.py
juju/delta.py
juju/errors.py
juju/exceptions.py
juju/jasyncio.py
juju/juju.py
juju/machine.py
juju/names.py
juju/offerendpoints.py
juju/origin.py
juju/placement.py
juju/provisioner.py
juju/py.typed
juju/relation.py
juju/remoteapplication.py
juju/secrets.py
juju/status.py
juju/tag.py
juju/unit.py
juju/url.py
juju/user.py
juju/utils.py
juju/version.py
juju/client/__init__.py
juju/client/_client.py
juju/client/_client1.py
juju/client/_client10.py
juju/client/_client11.py
juju/client/_client12.py
juju/client/_client17.py
juju/client/_client19.py
juju/client/_client2.py
juju/client/_client20.py
juju/client/_client3.py
juju/client/_client4.py
juju/client/_client5.py
juju/client/_client6.py
juju/client/_client7.py
juju/client/_client8.py
juju/client/_client9.py
juju/client/_definitions.py
juju/client/client.py
juju/client/codegen.py
juju/client/connection.py
juju/client/connector.py
juju/client/facade.py
juju/client/facade_versions.py
juju/client/flags.py
juju/client/gocookies.py
juju/client/jujudata.py
juju/client/overrides.py
juju/client/runner.py
juju/client/proxy/__init__.py
juju/client/proxy/factory.py
juju/client/proxy/proxy.py
juju/client/proxy/kubernetes/__init__.py
juju/client/proxy/kubernetes/proxy.py
juju/model/__init__.py
juju/model/_idle.py
juju-3.6.1.3.dist-info/licenses/LICENSE
juju-3.6.1.3.dist-info/METADATA
juju-3.6.1.3.dist-info/WHEEL
juju-3.6.1.3.dist-info/top_level.txt
juju-3.6.1.3.dist-info/RECORD
